md_tw.py
markdown_textwrap/__init__.py
markdown_textwrap/_version.py
markdown_textwrap-0.2.1.dist-info/DESCRIPTION.rst
markdown_textwrap-0.2.1.dist-info/METADATA
markdown_textwrap-0.2.1.dist-info/RECORD
markdown_textwrap-0.2.1.dist-info/WHEEL
markdown_textwrap-0.2.1.dist-info/entry_points.txt
markdown_textwrap-0.2.1.dist-info/metadata.json
markdown_textwrap-0.2.1.dist-info/top_level.txt
