Metadata-Version: 2.0
Name: markdown-textwrap
Version: 0.2.1
Summary: Text wrap Markdown Documents
Home-page: https://git.ricketyspace.net/markdown-textwrap
Author: rsiddharth
Author-email: s@ricketyspace.net
License: GNU General Public License version 3 or later
Keywords: markdown text wrap textwrap
Platform: GNU/Linux
Classifier: Development Status :: 2 - Pre-Alpha
Classifier: Environment :: Console
Classifier: Intended Audience :: Developers
Classifier: Intended Audience :: End Users/Desktop
Classifier: License :: OSI Approved :: GNU General Public License v3 or later (GPLv3+)
Classifier: Operating System :: POSIX :: Linux
Classifier: Programming Language :: Python :: 3 :: Only
Classifier: Topic :: Documentation
Classifier: Topic :: Text Processing :: General
Classifier: Topic :: Utilities
Requires-Dist: mistune (==0.8.3)
